wanna/cli/__main__.py
wanna_ml_test-0.0.30.dist-info/entry_points.txt
wanna_ml_test-0.0.30.dist-info/WHEEL
wanna_ml_test-0.0.30.dist-info/METADATA
wanna_ml_test-0.0.30.dist-info/RECORD
