Metadata-Version: 2.1
Name: wanna-ml-test
Version: 0.0.30
Summary: CLI tool for managing ML projects on Vertex AI
Author: Joao Da Silva
Author-email: joao.silva1@avast.com
Requires-Python: >=3.7.1,<3.11
Classifier: Programming Language :: Python :: 3
Classifier: Programming Language :: Python :: 3.8
Classifier: Programming Language :: Python :: 3.9
Classifier: Programming Language :: Python :: 3.10
Provides-Extra: test
Requires-Dist: Jinja2 (>=3.1.2,<4.0.0)
Requires-Dist: PyGithub (>=1.55,<2.0)
Requires-Dist: PyYAML (>=5.4.0,<6.0.0)
Requires-Dist: case-converter (>=1.0.2,<2.0.0)
Requires-Dist: checksumdir (>=1.2.0,<2.0.0)
Requires-Dist: cookiecutter (>=1.7.3,<2.0.0)
Requires-Dist: cron-validator (>=1.0.6,<2.0.0)
Requires-Dist: email-validator (>=1.2.1,<2.0.0)
Requires-Dist: emoji (>=1.7.0,<2.0.0)
Requires-Dist: gitpython (>=3.1.27,<4.0.0)
Requires-Dist: halo (>=0.0.31,<0.0.32)
Requires-Dist: importlib-metadata (>=4.0,<5.0)
Requires-Dist: kfp (>=1.8.12,<2.0.0)
Requires-Dist: merge-args (>=0.1.4,<0.2.0)
Requires-Dist: packaging (>=21.3,<22.0)
Requires-Dist: pandas (>=1.3.3,<2.0.0)
Requires-Dist: pathvalidate (>=2.5.0,<3.0.0)
Requires-Dist: pydantic (>=1.9.0,<2.0.0)
Requires-Dist: python-on-whales (>=0.43.0,<0.44.0)
Requires-Dist: pyyaml-include (>=1.3,<2.0)
Requires-Dist: smart-open[gcs] (>=6.0,<7.0)
Requires-Dist: treelib (>=1.6.1,<2.0.0)
Requires-Dist: typer (>=0.4.1,<0.5.0)
Requires-Dist: waiting (>=1.4.1,<2.0.0)
